s3_vector_langchain/S3VectorStore.py
s3_vector_langchain/__init__.py
s3_vectors_langchain-0.1.1.dist-info/METADATA
s3_vectors_langchain-0.1.1.dist-info/WHEEL
s3_vectors_langchain-0.1.1.dist-info/top_level.txt
s3_vectors_langchain-0.1.1.dist-info/RECORD
