Metadata-Version: 2.4
Name: s3-vectors-langchain
Version: 0.1.1
Summary: LangChain VectorStore implementation using AWS S3 Vectors
Author-email: Swagata Roy <r.swagata98@gmail.com>
Project-URL: Homepage, https://github.com/SwagataRoy98/s3-vector-langchain
Requires-Python: >=3.8
Requires-Dist: boto3
Requires-Dist: langchain
Requires-Dist: botocore
